skres/__init__.py
skres/hello.py
skres/skres.py
skres/salut/__init__.py
skres/salut/coucou.py
tests/__init__.py
skres-0.0.14.dist-info/LICENSE
skres-0.0.14.dist-info/METADATA
skres-0.0.14.dist-info/WHEEL
skres-0.0.14.dist-info/top_level.txt
skres-0.0.14.dist-info/RECORD
